Metadata-Version: 2.1
Name: TCGCSUtils
Version: 1.0.7
Summary: A lib to easily save or read files in GCS
Author: Maycon Vinicius Guimarães
Author-email: maycon.guimaraes@tc.com.br
License: UNKNOWN
Platform: UNKNOWN
License-File: LICENSE.txt
